lips/__init__.py
lips/utils.py
lips/augmented_simulators/__init__.py
lips/augmented_simulators/augmented_simulator.py
lips/augmented_simulators/hyperParameterTuner.py
lips/augmented_simulators/tensorflow_simulator.py
lips/augmented_simulators/torch_simulator.py
lips/augmented_simulators/tensorflow_models/__init__.py
lips/augmented_simulators/tensorflow_models/fully_connected.py
lips/augmented_simulators/tensorflow_models/airfoil/__init__.py
lips/augmented_simulators/tensorflow_models/airfoil/fully_connected.py
lips/augmented_simulators/tensorflow_models/powergrid/__init__.py
lips/augmented_simulators/tensorflow_models/powergrid/fully_connected.py
lips/augmented_simulators/tensorflow_models/powergrid/leap_net.py
lips/augmented_simulators/tensorflow_models/powergrid/resnet.py
lips/augmented_simulators/tensorflow_models/powergrid/utils.py
lips/augmented_simulators/torch_models/__init__.py
lips/augmented_simulators/torch_models/fully_connected.py
lips/augmented_simulators/torch_models/gnn.py
lips/augmented_simulators/torch_models/gnn_powergrid_utils.py
lips/augmented_simulators/torch_models/u_net.py
lips/augmented_simulators/torch_models/utils.py
lips/benchmark/__init__.py
lips/benchmark/airfransBenchmark.py
lips/benchmark/benchmark.py
lips/benchmark/powergridBenchmark.py
lips/benchmark/wheelBenchmark.py
lips/config/__init__.py
lips/config/configmanager.py
lips/dataset/__init__.py
lips/dataset/airfransDataSet.py
lips/dataset/dataSet.py
lips/dataset/pneumaticWheelDataSet.py
lips/dataset/powergridDataSet.py
lips/dataset/sampler.py
lips/dataset/scaler/__init__.py
lips/dataset/scaler/powergrid_scaler.py
lips/dataset/scaler/rolling_scaler.py
lips/dataset/scaler/scaler.py
lips/dataset/scaler/standard_scaler.py
lips/dataset/scaler/standard_scaler_iterative.py
lips/dataset/scaler/standard_scaler_per_channel.py
lips/dataset/utils/__init__.py
lips/dataset/utils/powergrid_utils.py
lips/evaluation/__init__.py
lips/evaluation/airfrans_evaluation.py
lips/evaluation/evaluation.py
lips_benchmark-0.2.7.dist-info/LICENSE
lips_benchmark-0.2.7.dist-info/METADATA
lips_benchmark-0.2.7.dist-info/WHEEL
lips_benchmark-0.2.7.dist-info/top_level.txt
lips_benchmark-0.2.7.dist-info/RECORD
