Metadata-Version: 2.1
Name: lips-benchmark
Version: 0.2.7
Summary: LIPS : Learning Industrial Physical Simulation benchmark suite
Home-page: https://github.com/IRT-SystemX/LIPS
Author: Milad Leyli-abadi
Author-email: milad.leyli-abadi@irt-systemx.fr
License: MPL
Keywords: Physical system solver,augmented simulator,benchmarking
Classifier: Development Status :: 4 - Beta
Classifier: Programming Language :: Python :: 3.6
Classifier: Programming Language :: Python :: 3.7
Classifier: Programming Language :: Python :: 3.8
Classifier: Programming Language :: Python :: 3.9
Classifier: Programming Language :: Python :: 3.10
Classifier: License :: OSI Approved :: Mozilla Public License 2.0 (MPL 2.0)
Classifier: Intended Audience :: Developers
Classifier: Intended Audience :: Education
Classifier: Intended Audience :: Science/Research
Classifier: Natural Language :: English
License-File: LICENSE
Requires-Dist: numpy ==1.25.2
Requires-Dist: scikit-learn
Requires-Dist: tqdm
Requires-Dist: matplotlib
Requires-Dist: scipy ==1.11.4
Requires-Dist: six
Requires-Dist: pathlib
Requires-Dist: numba
Provides-Extra: codabench
Requires-Dist: filelock ==3.7.1 ; extra == 'codabench'
Requires-Dist: json2table ==1.1.5 ; extra == 'codabench'
Requires-Dist: loguru ==0.6.0 ; extra == 'codabench'
Requires-Dist: PyYAML ==6.0 ; extra == 'codabench'
Requires-Dist: tqdm ==4.62.3 ; extra == 'codabench'
Requires-Dist: grid2op ==1.9.8 ; extra == 'codabench'
Requires-Dist: pybind11 ==2.8.1 ; extra == 'codabench'
Requires-Dist: lightsim2grid ==0.8.1 ; extra == 'codabench'
Requires-Dist: leap-net ==0.0.5 ; extra == 'codabench'
Requires-Dist: protobuf ==3.20.2 ; extra == 'codabench'
Requires-Dist: pandapower ==2.8.0 ; extra == 'codabench'
Requires-Dist: pandas ==1.5.3 ; extra == 'codabench'
Requires-Dist: jupyter ; extra == 'codabench'
Requires-Dist: tensorflow ==2.8.1 ; extra == 'codabench'
Requires-Dist: torch ==2.0.1 ; extra == 'codabench'
Requires-Dist: imageio ==2.34.0 ; extra == 'codabench'
Requires-Dist: plotly ==5.20.0 ; extra == 'codabench'
Provides-Extra: docs
Requires-Dist: numpydoc >=0.9.2 ; extra == 'docs'
Requires-Dist: sphinx >=2.4.4 ; extra == 'docs'
Requires-Dist: sphinx-rtd-theme >=0.4.3 ; extra == 'docs'
Requires-Dist: sphinxcontrib-trio >=1.1.0 ; extra == 'docs'
Requires-Dist: autodocsumm >=0.1.13 ; extra == 'docs'
Requires-Dist: gym >=0.17.2 ; extra == 'docs'
Provides-Extra: recommended
Requires-Dist: grid2op ==1.9.8 ; extra == 'recommended'
Requires-Dist: pybind11 ==2.8.1 ; extra == 'recommended'
Requires-Dist: lightsim2grid ==0.8.1 ; extra == 'recommended'
Requires-Dist: leap-net ==0.0.5 ; extra == 'recommended'
Requires-Dist: protobuf ==3.20.2 ; extra == 'recommended'
Requires-Dist: pandapower ==2.8.0 ; extra == 'recommended'
Requires-Dist: pandas ==1.5.3 ; extra == 'recommended'
Requires-Dist: jupyter ; extra == 'recommended'
Requires-Dist: tensorflow ==2.8.1 ; extra == 'recommended'
Requires-Dist: torch ==2.0.1 ; extra == 'recommended'
Requires-Dist: imageio ==2.34.0 ; extra == 'recommended'
Requires-Dist: plotly ==5.20.0 ; extra == 'recommended'
Provides-Extra: test
Requires-Dist: pytest ; extra == 'test'
Requires-Dist: pytest-cov ; extra == 'test'
Requires-Dist: pytest-html ; extra == 'test'
Requires-Dist: pytest-metadata ; extra == 'test'
Requires-Dist: ipykernel ; extra == 'test'
Requires-Dist: pylint ; extra == 'test'
Requires-Dist: pylint-exit ; extra == 'test'
Requires-Dist: jupytext ; extra == 'test'
Requires-Dist: grid2op ==1.9.8 ; extra == 'test'
Requires-Dist: pybind11 ==2.8.1 ; extra == 'test'
Requires-Dist: lightsim2grid ==0.8.1 ; extra == 'test'
Requires-Dist: leap-net ==0.0.5 ; extra == 'test'
Requires-Dist: protobuf ==3.20.2 ; extra == 'test'
Requires-Dist: pandapower ==2.8.0 ; extra == 'test'
Requires-Dist: pandas ==1.5.3 ; extra == 'test'
Requires-Dist: jupyter ; extra == 'test'
Requires-Dist: tensorflow ==2.8.1 ; extra == 'test'
Requires-Dist: torch ==2.0.1 ; extra == 'test'
Requires-Dist: imageio ==2.34.0 ; extra == 'test'
Requires-Dist: plotly ==5.20.0 ; extra == 'test'
Requires-Dist: numpydoc >=0.9.2 ; extra == 'test'
Requires-Dist: sphinx >=2.4.4 ; extra == 'test'
Requires-Dist: sphinx-rtd-theme >=0.4.3 ; extra == 'test'
Requires-Dist: sphinxcontrib-trio >=1.1.0 ; extra == 'test'
Requires-Dist: autodocsumm >=0.1.13 ; extra == 'test'
Requires-Dist: gym >=0.17.2 ; extra == 'test'
Requires-Dist: filelock ==3.7.1 ; extra == 'test'
Requires-Dist: json2table ==1.1.5 ; extra == 'test'
Requires-Dist: loguru ==0.6.0 ; extra == 'test'
Requires-Dist: PyYAML ==6.0 ; extra == 'test'
Requires-Dist: tqdm ==4.62.3 ; extra == 'test'
